cloudcheck/__init__.py
cloudcheck/cloudcheck.cpython-313-arm-linux-musleabihf.so
cloudcheck/helpers.py
cloudcheck/providers/__init__.py
cloudcheck/providers/akamai.py
cloudcheck/providers/alibaba.py
cloudcheck/providers/amazon.py
cloudcheck/providers/arvancloud.py
cloudcheck/providers/backblaze.py
cloudcheck/providers/baidu.py
cloudcheck/providers/base.py
cloudcheck/providers/cachefly.py
cloudcheck/providers/cdnetworks.py
cloudcheck/providers/cisco.py
cloudcheck/providers/cloudflare.py
cloudcheck/providers/cloudfront.py
cloudcheck/providers/ddosguard.py
cloudcheck/providers/dell.py
cloudcheck/providers/digitalocean.py
cloudcheck/providers/dod.py
cloudcheck/providers/fastly.py
cloudcheck/providers/fbi.py
cloudcheck/providers/gabia.py
cloudcheck/providers/gcore.py
cloudcheck/providers/github.py
cloudcheck/providers/gocache.py
cloudcheck/providers/google.py
cloudcheck/providers/heroku.py
cloudcheck/providers/hetzner.py
cloudcheck/providers/hostway.py
cloudcheck/providers/hpe.py
cloudcheck/providers/huawei.py
cloudcheck/providers/ibm.py
cloudcheck/providers/imperva.py
cloudcheck/providers/kamatera.py
cloudcheck/providers/kinx.py
cloudcheck/providers/ktcloud.py
cloudcheck/providers/leaseweb.py
cloudcheck/providers/lgtelecom.py
cloudcheck/providers/microsoft.py
cloudcheck/providers/microsoft365.py
cloudcheck/providers/navercloud.py
cloudcheck/providers/nhncloud.py
cloudcheck/providers/oracle.py
cloudcheck/providers/ovh.py
cloudcheck/providers/qrator.py
cloudcheck/providers/quiccloud.py
cloudcheck/providers/rackspace.py
cloudcheck/providers/ru_fso.py
cloudcheck/providers/salesforce.py
cloudcheck/providers/scaleway.py
cloudcheck/providers/skbroadband.py
cloudcheck/providers/stormwall.py
cloudcheck/providers/sucuri.py
cloudcheck/providers/tencent.py
cloudcheck/providers/uk_mod.py
cloudcheck/providers/wasabi.py
cloudcheck/providers/x4b.py
cloudcheck/providers/yandex.py
cloudcheck/providers/zoho.py
cloudcheck/providers/zscaler.py
cloudcheck-9.2.0.dist-info/METADATA
cloudcheck-9.2.0.dist-info/WHEEL
cloudcheck.libs/libgcc_s-262c4f60.so.1
cloudcheck-9.2.0.dist-info/RECORD
