Metadata-Version: 2.4
Name: cloudcheck
Version: 9.2.0
Summary: Detailed database of cloud providers. Instantly look up a domain or IP address
Home-Page: https://github.com/blacklanternsecurity/cloudcheck
Requires-Python: >=3.9
